helloasso_python/.DS_Store
helloasso_python/__init__.py
helloasso_python/api_client.py
helloasso_python/api_response.py
helloasso_python/configuration.py
helloasso_python/exceptions.py
helloasso_python/py.typed
helloasso_python/rest.py
helloasso_python/api/__init__.py
helloasso_python/api/annuaire_api.py
helloasso_python/api/checkout_api.py
helloasso_python/api/commandes_api.py
helloasso_python/api/formulaires_api.py
helloasso_python/api/liste_de_valeurs_api.py
helloasso_python/api/organisation_api.py
helloasso_python/api/organization_public_configurations_api.py
helloasso_python/api/paiements_api.py
helloasso_python/api/partenaires_api.py
helloasso_python/api/reus_fiscaux_api.py
helloasso_python/api/tags_api.py
helloasso_python/api/utilisateurs_api.py
helloasso_python/models/__init__.py
helloasso_python/models/ha_trust_contract_legal_information_address_address_dto.py
helloasso_python/models/hello_asso_api_v5_models_account_company_legal_status_model.py
helloasso_python/models/hello_asso_api_v5_models_account_organism_category_model.py
helloasso_python/models/hello_asso_api_v5_models_accounts_clients_api_client_model.py
helloasso_python/models/hello_asso_api_v5_models_accounts_clients_public_put_api_client_request.py
helloasso_python/models/hello_asso_api_v5_models_api_notifications_api_notification_type.py
helloasso_python/models/hello_asso_api_v5_models_api_notifications_api_url_notification_model.py
helloasso_python/models/hello_asso_api_v5_models_api_notifications_post_api_url_notification_body.py
helloasso_python/models/hello_asso_api_v5_models_carts_checkout_intent_response.py
helloasso_python/models/hello_asso_api_v5_models_carts_checkout_payer.py
helloasso_python/models/hello_asso_api_v5_models_carts_checkout_term.py
helloasso_python/models/hello_asso_api_v5_models_carts_init_checkout_body.py
helloasso_python/models/hello_asso_api_v5_models_carts_init_checkout_response.py
helloasso_python/models/hello_asso_api_v5_models_common_contact_model.py
helloasso_python-1.0.8.dist-info/METADATA
helloasso_python-1.0.8.dist-info/WHEEL
helloasso_python-1.0.8.dist-info/top_level.txt
helloasso_python-1.0.8.dist-info/RECORD
